{"columns":[{"kind":"Default","name":"avg_loss","num_defaults":0,"num_rows":18},{"kind":"Default","name":"avg_win","num_defaults":0,"num_rows":18},{"kind":"Default","name":"date","num_defaults":0,"num_rows":18},{"kind":"Default","name":"losing_trades","num_defaults":0,"num_rows":18},{"kind":"Sparse","name":"max_drawdown","num_defaults":18,"num_rows":18},{"kind":"Default","name":"total_pnl","num_defaults":0,"num_rows":18},{"kind":"Default","name":"total_trades","num_defaults":0,"num_rows":18},{"kind":"Sparse","name":"win_rate","num_defaults":18,"num_rows":18},{"kind":"Sparse","name":"winning_trades","num_defaults":18,"num_rows":18}],"types_serialization_versions":{"string":1},"version":1}